pyasuswrt/__init__.py
pyasuswrt/asuswrt.py
pyasuswrt/exceptions.py
pyasuswrt/helpers.py
pyasuswrt-0.1.21.dist-info/LICENSE
pyasuswrt-0.1.21.dist-info/METADATA
pyasuswrt-0.1.21.dist-info/WHEEL
pyasuswrt-0.1.21.dist-info/top_level.txt
pyasuswrt-0.1.21.dist-info/RECORD
