Metadata-Version: 2.1
Name: pyasuswrt
Version: 0.1.21
Summary: Api wrapper for Asuswrt https://www.asus.com/ASUSWRT/ using protocol HTTP
Home-page: https://github.com/ollo69/pyasuswrt
Download-URL: https://github.com/ollo69/pyasuswrt/archive/0.1.21.tar.gz
Author: ollo69
Author-email: ollo69@users.noreply.github.com
License: MIT
Keywords: asuswrt,asuswrt wrapper
Classifier: Development Status :: 3 - Alpha
Classifier: Intended Audience :: Developers
Classifier: Topic :: Software Development :: Libraries
Classifier: License :: OSI Approved :: MIT License
Classifier: Operating System :: OS Independent
Classifier: Programming Language :: Python :: 3
Requires-Python: >=3.7
License-File: LICENSE
Requires-Dist: aiohttp >=3.7.4
